heytorvas/__init__.py
heytorvas/main.py
heytorvas-0.0.9.dist-info/METADATA
heytorvas-0.0.9.dist-info/WHEEL
heytorvas-0.0.9.dist-info/entry_points.txt
heytorvas-0.0.9.dist-info/RECORD
