Metadata-Version: 2.1
Name: heytorvas
Version: 0.0.9
Summary: Heytor Victor's Portfolio
Author: Heytor Victor
Author-email: heytor@heytor.dev
Requires-Python: >=3.8,<4.0
Classifier: Programming Language :: Python :: 3
Classifier: Programming Language :: Python :: 3.8
Classifier: Programming Language :: Python :: 3.9
Classifier: Programming Language :: Python :: 3.10
Classifier: Programming Language :: Python :: 3.11
Classifier: Programming Language :: Python :: 3.12
Classifier: Programming Language :: Python :: 3.13
Requires-Dist: pytest (==8.3.3)
Requires-Dist: rich (==13.9.4)
Requires-Dist: typer (==0.13.1)
